greetlib/__init__.py
greetlib/greetings.py
greetlib-0.2.0.dist-info/LICENSE
greetlib-0.2.0.dist-info/METADATA
greetlib-0.2.0.dist-info/WHEEL
greetlib-0.2.0.dist-info/top_level.txt
greetlib-0.2.0.dist-info/RECORD
