Metadata-Version: 2.1
Name: greetlib
Version: 0.2.0
Summary: A simple package for generating greetings in different languages
Home-page: https://github.com/OlaAkindele/greeting-package.git
Author: Ola
Author-email: akindele.ok@gmail.com
Classifier: Programming Language :: Python :: 3
Classifier: License :: OSI Approved :: MIT License
Classifier: Operating System :: OS Independent
Requires-Python: >=3.9
License-File: LICENSE
